cpr_sdk/__init__.py
cpr_sdk/cli/search.py
cpr_sdk/config.py
cpr_sdk/data_adaptors.py
cpr_sdk/exceptions.py
cpr_sdk/models/__init__.py
cpr_sdk/models/search.py
cpr_sdk/orchestration/hooks.py
cpr_sdk/parser_models.py
cpr_sdk/pipeline_general_models.py
cpr_sdk/resources/sensitive_query_terms.tsv
cpr_sdk/result.py
cpr_sdk/s3.py
cpr_sdk/search_adaptors.py
cpr_sdk/search_intention_testing/README.md
cpr_sdk/search_intention_testing/executors.py
cpr_sdk/search_intention_testing/models.py
cpr_sdk/ssm.py
cpr_sdk/tools_agents/README.md
cpr_sdk/tools_agents/scripts/human_in_the_loop_document_search.py
cpr_sdk/tools_agents/scripts/search_planner.py
cpr_sdk/tools_agents/tools/genai.py
cpr_sdk/tools_agents/tools/search.py
cpr_sdk/utils.py
cpr_sdk/version.py
cpr_sdk/vespa.py
cpr_sdk/yql_builder.py
cpr_sdk-4.3.0.dist-info/METADATA
cpr_sdk-4.3.0.dist-info/WHEEL
cpr_sdk-4.3.0.dist-info/entry_points.txt
cpr_sdk-4.3.0.dist-info/licenses/LICENSE
cpr_sdk-4.3.0.dist-info/RECORD
