Metadata-Version: 2.4
Name: cpr_sdk
Version: 4.3.0
Summary: 
License: LICENSE
License-File: LICENSE
Author: CPR Tech
Author-email: tech@climatepolicyradar.org
Requires-Python: >=3.10,<3.14
Classifier: Intended Audience :: Science/Research
Classifier: Programming Language :: Python :: 3
Classifier: Topic :: Scientific/Engineering :: Artificial Intelligence
Provides-Extra: datasets
Provides-Extra: orchestration
Provides-Extra: vespa
Requires-Dist: aws-error-utils (>=2.7.0,<3)
Requires-Dist: boto3 (>=1.35.86,<2)
Requires-Dist: datasets (>=3.2.0,<4)
Requires-Dist: datasets ; extra == "datasets"
Requires-Dist: deprecation (>=2.1.0,<3)
Requires-Dist: flatten-dict (>=0.4.2,<1)
Requires-Dist: greenlet (>=3.3.1,<4.0.0)
Requires-Dist: langdetect (>=1.0.9,<2)
Requires-Dist: pandas (>=2.2.3,<3)
Requires-Dist: prefect[slack] ; extra == "orchestration"
Requires-Dist: pydantic (>=2.10.4,<3)
Requires-Dist: pytest-asyncio (>=1.1.0,<2)
Requires-Dist: pyvespa ; extra == "vespa"
Requires-Dist: pyyaml ; extra == "vespa"
Requires-Dist: rich (>=13.9.4,<14)
Requires-Dist: sentence-transformers ; extra == "vespa"
Requires-Dist: torch ; extra == "vespa"
Requires-Dist: tqdm (>=4.67.1,<5)
Project-URL: Changelog, https://github.com/climatepolicyradar/cpr-sdk/blob/main/CHANGELOG.md
Project-URL: Homepage, https://github.com/climatepolicyradar/cpr-sdk
Project-URL: Repository, https://github.com/climatepolicyradar/cpr-sdk
